touchutilcollection/__init__.py
touchutilcollection/ensure.py
touchutilcollection/events.py
touchutilcollection/extensions.py
touchutilcollection/external.py
touchutilcollection/layout.py
touchutilcollection/network.py
touchutilcollection/operator.py
touchutilcollection/parameter.py
touchutilcollection/profiling.py
touchutilcollection/tables.py
touchutilcollection/tdasync.py
touchutilcollection/timing.py
touchutilcollection/type.py
touchutilcollection/par_def/pargrouptypes.py
touchutilcollection/par_def/partypes.py
tdp_touchutilcollection-0.7.1.dist-info/METADATA
tdp_touchutilcollection-0.7.1.dist-info/WHEEL
tdp_touchutilcollection-0.7.1.dist-info/top_level.txt
tdp_touchutilcollection-0.7.1.dist-info/RECORD
