Metadata-Version: 2.4
Name: tdp-touchutilcollection
Version: 0.7.1
Summary: A collection of practical utilities for TouchDesigner.
Author-email: Wieland Hilker <Wieland@PlusPlus.One>
Project-URL: Website, https://plusplus.one
Project-URL: Repository, https://github.com/PlusPlusOneGmbH/Py_TouchUtilCollection
Keywords: TouchDesigner,Utility
Requires-Python: >=3.11
